FinMesh/__init__.py
FinMesh/auxiliary/__init__.py
FinMesh/auxiliary/token_setup.py
FinMesh/auxiliary/word_processing.py
FinMesh/edgar/__init__.py
FinMesh/edgar/_common.py
FinMesh/edgar/_parser.py
FinMesh/edgar/edgar.py
FinMesh/edgar/report.py
FinMesh/edgar/research.py
FinMesh/iex/__init__.py
FinMesh/iex/_common.py
FinMesh/iex/account.py
FinMesh/iex/class.py
FinMesh/iex/forex.py
FinMesh/iex/market.py
FinMesh/iex/premium.py
FinMesh/iex/stock.py
FinMesh/iex/tested.py
FinMesh/polygon/__init__.py
FinMesh/polygon/_common.py
FinMesh/polygon/forex.py
FinMesh/polygon/options.py
FinMesh/polygon/reference.py
FinMesh/polygon/stocks.py
FinMesh/usgov/__init__.py
FinMesh/usgov/fred.py
FinMesh/usgov/yieldcurve.py
iex/__init__.py
iex/_common.py
iex/account.py
iex/stock.py
usgov/__init__.py
usgov/fred.py
usgov/yieldcurve.py
FinMesh-2.2.1.dist-info/LICENSE.md
FinMesh-2.2.1.dist-info/METADATA
FinMesh-2.2.1.dist-info/WHEEL
FinMesh-2.2.1.dist-info/top_level.txt
FinMesh-2.2.1.dist-info/RECORD
