Metadata-Version: 2.1
Name: FinMesh
Version: 2.2.1
Summary: A Python wrapper to bring together various financial APIs.
Home-page: https://finmesh.readthedocs.io/
Author: Michael Hartmann
Author-email: michaelpeterhartmann94@gmail.com.com
License: UNKNOWN
Keywords: Finance,API,DCF,IEX,EDGAR,FRED,interest rates
Platform: UNKNOWN
Classifier: Programming Language :: Python :: 3
Requires-Python: >3.6
License-File: LICENSE.md
